libcoapy/__init__.py
libcoapy/libcoapy.py
libcoapy/llapi.py
libcoapy-2025.8.22.data/scripts/coap-gui
libcoapy-2025.8.22.data/scripts/coarl
libcoapy-2025.8.22.dist-info/licenses/LICENSE.txt
libcoapy-2025.8.22.dist-info/METADATA
libcoapy-2025.8.22.dist-info/WHEEL
libcoapy-2025.8.22.dist-info/top_level.txt
libcoapy-2025.8.22.dist-info/RECORD
