Metadata-Version: 2.4
Name: libcoapy
Version: 2025.8.22
Summary: Python module to communicate over the CoAP protocol
Author-email: Mario Kicherer <dev@kicherer.org>
License: Permission is hereby granted, free of charge, to any person obtaining a copy
Project-URL: Homepage, https://github.com/anyc/libcoapy/
Project-URL: Issues, https://github.com/anyc/libcoapy/issues
Keywords: CoAP,network,libcoap
Classifier: Programming Language :: Python :: 3
Requires-Python: >=3.0
License-File: LICENSE.txt
Provides-Extra: ifaddr
Requires-Dist: ifaddr; extra == "ifaddr"
Dynamic: license-file
